Workbook
Name Aluguel_condomínio_e_IPTU_imóvel: Premissas!#REF!
Name assinatura: Premissas!$B$25
Name Benefícios_Funcionários_Assistência_Médica: Premissas!#REF!
Name Benefícios_Funcionários_VISA_VALE: Premissas!#REF!
Name Cancelamento_da_transferência_de_proprietário: Premissas!#REF!
Name Cancelamento_do_Gravame: Premissas!#REF!
Name Company: Premissas!$B$7
Name Comunicação_de_venda_arrendamento_mercantil: Premissas!#REF!
Name Consulta_a_base_de_dados__Estadual_e_Federal: Premissas!#REF!
Name Consulta_de_histórico_do_veículo: Premissas!#REF!
Name csll: Premissas!$B$20
Name currency: Premissas!$B$10
Name Custo_Mensal_Hospedagem_dedicada: Premissas!#REF!
Name Custo_Mensal_Telefonia_e_Internet: Premissas!#REF!
Name Custo_Sistema_Cancel_Transf_Proprietário: Premissas!#REF!
Name Custo_Sistema_Cancelamento_Gravame: Premissas!#REF!
Name Custo_Sistema_Comunicação_de_venda_arrendamento_mercantil: Premissas!#REF!
Name Custo_Sistema_Consulta_Base_Dados: Premissas!#REF!
Name Custo_Sistema_Consulta_Histórico: Premissas!#REF!
Name Custo_Sistema_Quitação_Baixa_Gravame: Premissas!#REF!
Name Custo_Sistema_Registro_Contrato_Alienação_Fiduciária: Premissas!#REF!
Name Custo_Sistema_Registro_Gravame: Premissas!#REF!
Name Custo_Sistema_Transferência: Premissas!#REF!
Name Demanda_Acre: Premissas!#REF!
Name Demanda_Alagoas: Premissas!#REF!
Name Demanda_Amapá: Premissas!#REF!
Name Demanda_Amazonas: Premissas!#REF!
Name Demanda_Bahia: Premissas!#REF!
Name Demanda_Ceará: Premissas!#REF!
Name Demanda_Distrito_Federal: Premissas!#REF!
Name Demanda_Espírito_Santo: Premissas!#REF!
Name Demanda_Goiás: Premissas!#REF!
Name Demanda_Maranhão: Premissas!#REF!
Name Demanda_Mato_Grosso: Premissas!#REF!
Name Demanda_Mato_Grosso_do_Sul: Premissas!#REF!
Name Demanda_Minas_Gerais: Premissas!#REF!
Name Demanda_Pará: Premissas!#REF!
Name Demanda_Paraíba: Premissas!#REF!
Name Demanda_Paraná: Premissas!#REF!
Name Demanda_Pernambuco: Premissas!#REF!
Name Demanda_Piauí: Premissas!#REF!
Name Demanda_Rio_de_Janeiro: Premissas!#REF!
Name Demanda_Rio_Grande_do_Norte: Premissas!#REF!
Name Demanda_Rio_Grande_do_Sul: Premissas!#REF!
Name Demanda_Rondônia: Premissas!#REF!
Name Demanda_Roraima: Premissas!#REF!
Name Demanda_Santa_Catarina: Premissas!#REF!
Name Demanda_São_Paulo: Premissas!#REF!
Name Demanda_Sergipe: Premissas!#REF!
Name Demanda_Tocantins: Premissas!#REF!
Name Desconto_em_relação_ao_concorrente: Premissas!#REF!
Name Desenvolvimento_Novos_Produtos_Porcentual_do_faturamento: Premissas!#REF!
Name Desp_MKT_Divulgação: Premissas!#REF!
Name Desp_MKT_Relacionamento: Premissas!#REF!
Name Desp_MKT_Viagens: Premissas!#REF!
Name Desp_Novo_Escritório_Comercial_Aluguel_condomínio_e_IPTU_imóvel: Premissas!#REF!
Name Desp_Novo_Escritório_Comercial_Infra_estrutura_geral: Premissas!#REF!
Name Desp_Novo_Escritório_Comercial_Telefonia: Premissas!#REF!
Name Despesa_Mensal_Aluguel__condomínio_e_IPTU_imóvel: Premissas!#REF!
Name Despesa_Mensal_Assessoria_jurídica: Premissas!#REF!

Sheet Premissas
A1: PREMISSAS
A2: =CONCATENATE(Company, ": ",start, " - ",end) -> Histyle: Mês 1 - Mês 60
A4: Observação: passe o ícone (do mouse) sobre as células para ter acesso à explicação do memorial de cálculo
A6: PREMISSAS GERAIS
A7: Nome da Empresa | B7: Histyle
A8: Ano de Início da Operação | B8: Mês 1 | C8: NÃO ALTERAR
A9: Ano Final da Projeção | B9: Mês 60 | C9: NÃO ALTERAR
A10: Moeda | B10: R$ | C10: NÃO ALTERAR
A11: Denominação | B11: 000's | C11: NÃO ALTERAR
A14: Encargos e impostos
A15: Reajuste de salários (Selic, base 2023) | B15: 0.1325 | C15: NÃO ALTERAR
A16: ICMS | B16: 0.12 | C16: NÃO ALTERAR
A17: PIS/COFINS | B17: 0.0365 | C17: NÃO ALTERAR
A18: Impostos sobre faturamento | B18: =ISS+B17 -> 0.1565 | C18: NÃO ALTERAR
A19: IR | B19: 0.25 | C19: NÃO ALTERAR
A20: CSLL | B20: 0.09 | C20: NÃO ALTERAR
A22: Premissas comerciais | B22: Ano 1 | C22: Ano 2 | D22: Ano 3 | E22: Ano 4 | F22: Ano 5
A23: Vendas de Produtos/Serviços (Receita) Assinatura | C23: =0.1*(C25+C27) -> 150 | D23: =0.1*(D25+D27) -> 100 | E23: =0.1*(E25+E27) -> 550 | F23: =0.1*(F25+F27) -> 370
A24: Ticket médio nas vendas Assinatura | B24: 75 | C24: 75 | D24: 75 | E24: 75 | F24: 75
A25: Vendas de Produtos/Serviços (Receita) Jogo 1 | B25: 900 | C25: 1500 | D25: 1000 | E25: 1500 | F25: 1200
A26: Ticket médio nas vendas Jogo1 | B26: 65 | C26: 65 | D26: 65 | E26: 65 | F26: 65
A27: Venda de Produtos/Serviços 2 (Receita) Jogo 2 | B27: 0 | C27: =(B27*1.05)*1.5 -> 0 | D27: =C27*1.05*1.33333 -> 0 | E27: 4000 | F27: 2500
A28: Ticket médio 2 Jogo 2 | B28: 55 | C28: 55 | D28: 55 | E28: 55 | F28: 55
A29: Jogo 1 vendido por mês | B29: =assinatura/12 -> 75 | C29: =C25/12 -> 125 | D29: =D25/12 -> 83.333333 | E29: =E25/12 -> 125 | F29: =F25/12 -> 100
A30: Jogo 2 vendido por mês | B30: =B27/12 -> 0 | C30: =C27/12 -> 0 | D30: =D27/12 -> 0 | E30: =E27/12 -> 333.33333 | F30: =F27/12 -> 208.33333
A31: Assinaturas por mês | B31: =B23/12 -> 0 | C31: =C23/12 -> 12.5 | D31: =D23/12 -> 8.3333333 | E31: =E23/12 -> 45.833333 | F31: =F23/12 -> 30.833333
A32: Quantidade de itens vendidos por mês (1+2+assinatura) | B32: =(assinatura+(B27)+B23)/12 -> 75 | C32: =(assinatura+(C27)+C23)/12 -> 87.5 | D32: =(assinatura+(D27)+D23)/12 -> 83.333333 | E32: =(assinatura+(E27)+E23)/12 -> 454.16667 | F32: =(assinatura+(F27)+F23)/12 -> 314.16667
A33: Faturamento assinatura | B33: =B23*B24 -> 0 | C33: =C23*C24 -> 11250 | D33: =D23*D24 -> 7500 | E33: =E23*E24 -> 41250 | F33: =F23*F24 -> 27750
A34: Faturamento jogo 1 | B34: =assinatura*B26 -> 58500 | C34: =assinatura*C26 -> 58500 | D34: =assinatura*D26 -> 58500 | E34: =assinatura*E26 -> 58500 | F34: =assinatura*F26 -> 58500
A35: Faturamento jogo 2 | B35: =B28*B27 -> 0 | C35: =C28*C27 -> 0 | D35: =D28*D27 -> 0 | E35: =E28*E27 -> 220000 | F35: =F28*F27 -> 137500
A36: TOTAL | B36: =SUM(B33:B35) -> 58500 | C36: =SUM(C33:C35) -> 69750 | D36: =SUM(D33:D35) -> 66000 | E36: =SUM(E33:E35) -> 319750 | F36: =SUM(F33:F35) -> 223750

Sheet Receita
A1: RECEITA
A2: =CONCATENATE(Company, ": ",start, " - ",end) -> Histyle: Mês 1 - Mês 60
A3: Receita dos produtos vendidos | B3: =((assinatura/12))*0.2 -> 15 | C3: =((assinatura/12))*0.25 -> 18.75 | D3: =((assinatura/12))*0.3 -> 22.5 | E3: =((assinatura/12))*0.35 -> 26.25 | F3: =((assinatura/12))*0.4 -> 30 | G3: =((assinatura/12))*0.5 -> 37.5 | H3: =((assinatura/12))*0.6 -> 45 | I3: =((assinatura/12))*0.7 -> 52.5 | J3: =((assinatura/12))*0.8 -> 60 | K3: =((assinatura/12))*0.9 -> 67.5 | L3: =((assinatura/12)) -> 75 | M3: =((assinatura/12)) -> 75 | N3: =(Premissas!C25/12) -> 125 | O3: =(Premissas!C25/12) -> 125 | P3: =(Premissas!C25/12) -> 125 | Q3: =(Premissas!C25/12) -> 125 | R3: =(Premissas!C25/12) -> 125 | S3: =(Premissas!C25/12) -> 125 | T3: =(Premissas!C25/12) -> 125 | U3: =(Premissas!C25/12) -> 125 | V3: =(Premissas!C25/12) -> 125 | W3: =(Premissas!C25/12) -> 125 | X3: =(Premissas!C25/12) -> 125 | Y3: =(Premissas!C25/12) -> 125 | Z3: =(Premissas!D25/12) -> 83.333333 | AA3: =(Premissas!D25/12) -> 83.333333 | AB3: =(Premissas!D25/12) -> 83.333333 | AC3: =(Premissas!D25/12) -> 83.333333 | AD3: =(Premissas!D25/12) -> 83.333333 | AE3: =(Premissas!D25/12) -> 83.333333 | AF3: =(Premissas!D25/12) -> 83.333333 | AG3: =(Premissas!D25/12) -> 83.333333 | AH3: =(Premissas!D25/12) -> 83.333333 | AI3: =(Premissas!D25/12) -> 83.333333 | AJ3: =(Premissas!D25/12) -> 83.333333 | AK3: =(Premissas!D25/12) -> 83.333333 | AL3: =(Premissas!E25/12) -> 125 | AM3: =(Premissas!E25/12) -> 125 | AN3: =(Premissas!E25/12) -> 125 | AO3: =(Premissas!E25/12) -> 125 | AP3: =(Premissas!E25/12) -> 125 | AQ3: =(Premissas!E25/12) -> 125 | AR3: =(Premissas!E25/12) -> 125 | AS3: =(Premissas!E25/12) -> 125 | AT3: =(Premissas!E25/12) -> 125 | AU3: =(Premissas!E25/12) -> 125 | AV3: =(Premissas!E25/12) -> 125 | AW3: =(Premissas!E25/12) -> 125 | AX3: =(Premissas!F25/12) -> 100 | AY3: =(Premissas!F25/12) -> 100 | AZ3: =(Premissas!F25/12) -> 100 | BA3: =(Premissas!F25/12) -> 100 | BB3: =(Premissas!F25/12) -> 100 | BC3: =(Premissas!F25/12) -> 100 | BD3: =(Premissas!F25/12) -> 100 | BE3: =(Premissas!F25/12) -> 100 | BF3: =(Premissas!F25/12) -> 100 | BG3: =(Premissas!F25/12) -> 100 | BH3: =(Premissas!F25/12) -> 100 | BI3: =(Premissas!F25/12) -> 100
A4: Vendas ITEM 1 Jogo 1 | B4: 1 | C4: 2 | D4: 3 | E4: 4 | F4: 5 | G4: 6 | H4: 7 | I4: 8 | J4: 9 | K4: 10 | L4: 11 | M4: 12 | N4: 13 | O4: 14 | P4: 15 | Q4: 16 | R4: 17 | S4: 18 | T4: 19 | U4: 20 | V4: 21 | W4: 22 | X4: 23 | Y4: 24 | Z4: 25 | AA4: 26 | AB4: 27 | AC4: 28 | AD4: 29 | AE4: 30 | AF4: 31 | AG4: 32 | AH4: 33 | AI4: 34 | AJ4: 35 | AK4: 36 | AL4: 37 | AM4: 38 | AN4: 39 | AO4: 40 | AP4: 41 | AQ4: 42 | AR4: 43 | AS4: 44 | AT4: 45 | AU4: 46 | AV4: 47 | AW4: 48 | AX4: 49 | AY4: 50 | AZ4: 51 | BA4: 52 | BB4: 53 | BC4: 54 | BD4: 55 | BE4: 56 | BF4: 57 | BG4: 58 | BH4: 59 | BI4: 60
A5: Jogo 1 | B5: =(assinatura/12)*Premissas!B26 -> 4875 | C5: =B5 -> 4875 | D5: =C5 -> 4875 | E5: =D5 -> 4875 | F5: =E5 -> 4875 | G5: =F5 -> 4875 | H5: =G5 -> 4875 | I5: =H5 -> 4875 | J5: =I5 -> 4875 | ... M5: =L5 -> 4875 | N5: =(Premissas!C26/12)*Premissas!C25 -> 8125 | O5: =N5 -> 8125 | P5: =O5 -> 8125 | Q5: =P5 -> 8125 | R5: =Q5 -> 8125 | S5: =R5 -> 8125 | T5: =S5 -> 8125 | U5: =T5 -> 8125 | V5: =U5 -> 8125 | ... X5: =W5 -> 8125 | Y5: =(Premissas!D25/12)*Premissas!D26 -> 5416.6667 | Z5: =Y5 -> 5416.6667 | AA5: =Z5 -> 5416.6667 | AB5: =AA5 -> 5416.6667 | AC5: =AB5 -> 5416.6667 | AD5: =AC5 -> 5416.6667 | AE5: =AD5 -> 5416.6667 | AF5: =AE5 -> 5416.6667 | AG5: =AF5 -> 5416.6667 | ... AJ5: =AI5 -> 5416.6667 | AK5: =(Premissas!E25/12)*Premissas!E26 -> 8125 | AL5: =AK5 -> 8125 | AM5: =AL5 -> 8125 | AN5: =AM5 -> 8125 | AO5: =AN5 -> 8125 | AP5: =AO5 -> 8125 | AQ5: =AP5 -> 8125 | AR5: =AQ5 -> 8125 | AS5: =AR5 -> 8125 | ... AW5: =AV5 -> 8125 | AX5: =(Premissas!F25/12)*Premissas!F26 -> 6500 | AY5: =AX5 -> 6500 | AZ5: =AY5 -> 6500 | BA5: =AZ5 -> 6500 | BB5: =BA5 -> 6500 | BC5: =BB5 -> 6500 | BD5: =BC5 -> 6500 | BE5: =BD5 -> 6500 | BF5: =BE5 -> 6500 | ... BI5: =BH5 -> 6500
A6: TOTAL | B6: =B5 -> 4875 | C6: =C5 -> 4875 | D6: =D5 -> 4875 | E6: =E5 -> 4875 | F6: =F5 -> 4875 | G6: =G5 -> 4875 | H6: =H5 -> 4875 | I6: =I5 -> 4875 | ... BI6: =BI5 -> 6500
B7: =Premissas!B29 -> 75 | C7: =B7 -> 75 | D7: =C7 -> 75 | E7: =D7 -> 75 | F7: =E7 -> 75 | G7: =F7 -> 75 | H7: =G7 -> 75 | I7: =H7 -> 75 | J7: =I7 -> 75 | ... M7: =L7 -> 75 | N7: =Premissas!C29 -> 125 | O7: =N7 -> 125 | P7: =O7 -> 125 | Q7: =P7 -> 125 | R7: =Q7 -> 125 | S7: =R7 -> 125 | T7: =S7 -> 125 | U7: =T7 -> 125 | V7: =U7 -> 125 | ... Y7: =X7 -> 125 | Z7: =Premissas!D29 -> 83.333333 | AA7: =Z7 -> 83.333333 | AB7: =AA7 -> 83.333333 | AC7: =AB7 -> 83.333333 | AD7: =AC7 -> 83.333333 | AE7: =AD7 -> 83.333333 | AF7: =AE7 -> 83.333333 | AG7: =AF7 -> 83.333333 | AH7: =AG7 -> 83.333333 | ... AK7: =AJ7 -> 83.333333 | AL7: =Premissas!E29 -> 125 | AM7: =AL7 -> 125 | AN7: =AM7 -> 125 | AO7: =AN7 -> 125 | AP7: =AO7 -> 125 | AQ7: =AP7 -> 125 | AR7: =AQ7 -> 125 | AS7: =AR7 -> 125 | AT7: =AS7 -> 125 | ... AW7: =AV7 -> 125 | AX7: =Premissas!F29 -> 100 | AY7: =AX7 -> 100 | AZ7: =AY7 -> 100 | BA7: =AZ7 -> 100 | BB7: =BA7 -> 100 | BC7: =BB7 -> 100 | BD7: =BC7 -> 100 | BE7: =BD7 -> 100 | BF7: =BE7 -> 100 | ... BI7: =BH7 -> 100
A8: Vendas ITEM 2 Jogo 2 | B8: 1 | C8: 2 | D8: 3 | E8: 4 | F8: 5 | G8: 6 | H8: 7 | I8: 8 | J8: 9 | K8: 10 | L8: 11 | M8: 12 | N8: 13 | O8: 14 | P8: 15 | Q8: 16 | R8: 17 | S8: 18 | T8: 19 | U8: 20 | V8: 21 | W8: 22 | X8: 23 | Y8: 24 | Z8: 25 | AA8: 26 | AB8: 27 | AC8: 28 | AD8: 29 | AE8: 30 | AF8: 31 | AG8: 32 | AH8: 33 | AI8: 34 | AJ8: 35 | AK8: 36 | AL8: 37 | AM8: 38 | AN8: 39 | AO8: 40 | AP8: 41 | AQ8: 42 | AR8: 43 | AS8: 44 | AT8: 45 | AU8: 46 | AV8: 47 | AW8: 48 | AX8: 49 | AY8: 50 | AZ8: 51 | BA8: 52 | BB8: 53 | BC8: 54 | BD8: 55 | BE8: 56 | BF8: 57 | BG8: 58 | BH8: 59 | BI8: 60
A9: Jogo 2 | B9: =(Premissas!B27/12)*Premissas!B28 -> 0 | C9: =B9 -> 0 | D9: =C9 -> 0 | E9: =D9 -> 0 | F9: =E9 -> 0 | G9: =F9 -> 0 | H9: =G9 -> 0 | I9: =H9 -> 0 | J9: =I9 -> 0 | ... M9: =L9 -> 0 | N9: =(Premissas!C27/12)*Premissas!C28 -> 0 | O9: =N9 -> 0 | P9: =O9 -> 0 | Q9: =P9 -> 0 | R9: =Q9 -> 0 | S9: =R9 -> 0 | T9: =S9 -> 0 | U9: =T9 -> 0 | V9: =U9 -> 0 | ... Y9: =X9 -> 0 | Z9: =(Premissas!D27/12)*Premissas!D28 -> 0 | AA9: =Z9 -> 0 | AB9: =AA9 -> 0 | AC9: =AB9 -> 0 | AD9: =AC9 -> 0 | AE9: =AD9 -> 0 | AF9: =AE9 -> 0 | AG9: =AF9 -> 0 | AH9: =AG9 -> 0 | ... AK9: =AJ9 -> 0 | AL9: =(Premissas!E27/12)*Premissas!E28 -> 18333.333 | AM9: =AL9 -> 18333.333 | AN9: =AM9 -> 18333.333 | AO9: =AN9 -> 18333.333 | AP9: =AO9 -> 18333.333 | AQ9: =AP9 -> 18333.333 | AR9: =AQ9 -> 18333.333 | AS9: =AR9 -> 18333.333 | AT9: =AS9 -> 18333.333 | ... AW9: =AV9 -> 18333.333 | AX9: =(Premissas!F27/12)*Premissas!F28 -> 11458.333 | AY9: =AX9 -> 11458.333 | AZ9: =AY9 -> 11458.333 | BA9: =AZ9 -> 11458.333 | BB9: =BA9 -> 11458.333 | BC9: =BB9 -> 11458.333 | BD9: =BC9 -> 11458.333 | BE9: =BD9 -> 11458.333 | BF9: =BE9 -> 11458.333 | ... BI9: =BH9 -> 11458.333
A10: TOTAL | B10: =SUM(B9) -> 0 | C10: =SUM(C9) -> 0 | D10: =SUM(D9) -> 0 | E10: =SUM(E9) -> 0 | F10: =SUM(F9) -> 0 | G10: =SUM(G9) -> 0 | H10: =SUM(H9) -> 0 | I10: =SUM(I9) -> 0 | ... BI10: =SUM(BI9) -> 11458.333
B11: =Premissas!B30 -> 0 | C11: =B11 -> 0 | D11: =C11 -> 0 | E11: =D11 -> 0 | F11: =E11 -> 0 | G11: =F11 -> 0 | H11: =G11 -> 0 | I11: =H11 -> 0 | J11: =I11 -> 0 | ... M11: =L11 -> 0 | N11: =Premissas!C30 -> 0 | O11: =N11 -> 0 | P11: =O11 -> 0 | Q11: =P11 -> 0 | R11: =Q11 -> 0 | S11: =R11 -> 0 | T11: =S11 -> 0 | U11: =T11 -> 0 | V11: =U11 -> 0 | ... Y11: =X11 -> 0 | Z11: =Premissas!D30 -> 0 | AA11: =Z11 -> 0 | AB11: =AA11 -> 0 | AC11: =AB11 -> 0 | AD11: =AC11 -> 0 | AE11: =AD11 -> 0 | AF11: =AE11 -> 0 | AG11: =AF11 -> 0 | AH11: =AG11 -> 0 | ... AK11: =AJ11 -> 0 | AL11: =Premissas!E30 -> 333.33333 | AM11: =AL11 -> 333.33333 | AN11: =AM11 -> 333.33333 | AO11: =AN11 -> 333.33333 | AP11: =AO11 -> 333.33333 | AQ11: =AP11 -> 333.33333 | AR11: =AQ11 -> 333.33333 | AS11: =AR11 -> 333.33333 | AT11: =AS11 -> 333.33333 | ... AW11: =AV11 -> 333.33333 | AX11: =Premissas!F30 -> 208.33333 | AY11: =AX11 -> 208.33333 | AZ11: =AY11 -> 208.33333 | BA11: =AZ11 -> 208.33333 | BB11: =BA11 -> 208.33333 | BC11: =BB11 -> 208.33333 | BD11: =BC11 -> 208.33333 | BE11: =BD11 -> 208.33333 | BF11: =BE11 -> 208.33333 | ... BI11: =BH11 -> 208.33333
A12: Vendas ITEM 2 Assinatura | B12: 1 | C12: 2 | D12: 3 | E12: 4 | F12: 5 | G12: 6 | H12: 7 | I12: 8 | J12: 9 | K12: 10 | L12: 11 | M12: 12 | N12: 13 | O12: 14 | P12: 15 | Q12: 16 | R12: 17 | S12: 18 | T12: 19 | U12: 20 | V12: 21 | W12: 22 | X12: 23 | Y12: 24 | Z12: 25 | AA12: 26 | AB12: 27 | AC12: 28 | AD12: 29 | AE12: 30 | AF12: 31 | AG12: 32 | AH12: 33 | AI12: 34 | AJ12: 35 | AK12: 36 | AL12: 37 | AM12: 38 | AN12: 39 | AO12: 40 | AP12: 41 | AQ12: 42 | AR12: 43 | AS12: 44 | AT12: 45 | AU12: 46 | AV12: 47 | AW12: 48 | AX12: 49 | AY12: 50 | AZ12: 51 | BA12: 52 | BB12: 53 | BC12: 54 | BD12: 55 | BE12: 56 | BF12: 57 | BG12: 58 | BH12: 59 | BI12: 60
A13: Assinatura | B13: =(Premissas!B23/12)*Premissas!B24 -> 0 | C13: =B13 -> 0 | D13: =C13 -> 0 | E13: =D13 -> 0 | F13: =E13 -> 0 | G13: =F13 -> 0 | H13: =G13 -> 0 | I13: =H13 -> 0 | J13: =I13 -> 0 | ... M13: =L13 -> 0 | N13: =(Premissas!C23/12)*Premissas!C24 -> 937.5 | O13: =N13 -> 937.5 | P13: =O13 -> 937.5 | Q13: =P13 -> 937.5 | R13: =Q13 -> 937.5 | S13: =R13 -> 937.5 | T13: =S13 -> 937.5 | U13: =T13 -> 937.5 | V13: =U13 -> 937.5 | ... Y13: =X13 -> 937.5 | Z13: =(Premissas!D23/12)*Premissas!D24 -> 625 | AA13: =Z13 -> 625 | AB13: =AA13 -> 625 | AC13: =AB13 -> 625 | AD13: =AC13 -> 625 | AE13: =AD13 -> 625 | AF13: =AE13 -> 625 | AG13: =AF13 -> 625 | AH13: =AG13 -> 625 | ... AK13: =AJ13 -> 625 | AL13: =(Premissas!E23/12)*Premissas!E24 -> 3437.5 | AM13: =AL13 -> 3437.5 | AN13: =AM13 -> 3437.5 | AO13: =AN13 -> 3437.5 | AP13: =AO13 -> 3437.5 | AQ13: =AP13 -> 3437.5 | AR13: =AQ13 -> 3437.5 | AS13: =AR13 -> 3437.5 | AT13: =AS13 -> 3437.5 | ... AW13: =AV13 -> 3437.5 | AX13: =(Premissas!F23/12)*Premissas!F24 -> 2312.5 | AY13: =AX13 -> 2312.5 | AZ13: =AY13 -> 2312.5 | BA13: =AZ13 -> 2312.5 | BB13: =BA13 -> 2312.5 | BC13: =BB13 -> 2312.5 | BD13: =BC13 -> 2312.5 | BE13: =BD13 -> 2312.5 | BF13: =BE13 -> 2312.5 | ... BI13: =BH13 -> 2312.5
A14: TOTAL | B14: =SUM(B13) -> 0 | C14: =SUM(C13) -> 0 | D14: =SUM(D13) -> 0 | E14: =SUM(E13) -> 0 | F14: =SUM(F13) -> 0 | G14: =SUM(G13) -> 0 | H14: =SUM(H13) -> 0 | I14: =SUM(I13) -> 0 | ... BI14: =SUM(BI13) -> 2312.5
B15: =Premissas!B31 -> 0 | C15: =B15 -> 0 | D15: =C15 -> 0 | E15: =D15 -> 0 | F15: =E15 -> 0 | G15: =F15 -> 0 | H15: =G15 -> 0 | I15: =H15 -> 0 | J15: =I15 -> 0 | ... M15: =L15 -> 0 | N15: =Premissas!C31 -> 12.5 | O15: =N15 -> 12.5 | P15: =O15 -> 12.5 | Q15: =P15 -> 12.5 | R15: =Q15 -> 12.5 | S15: =R15 -> 12.5 | T15: =S15 -> 12.5 | U15: =T15 -> 12.5 | V15: =U15 -> 12.5 | ... Y15: =X15 -> 12.5 | Z15: =Premissas!D31 -> 8.3333333 | AA15: =Z15 -> 8.3333333 | AB15: =AA15 -> 8.3333333 | AC15: =AB15 -> 8.3333333 | AD15: =AC15 -> 8.3333333 | AE15: =AD15 -> 8.3333333 | AF15: =AE15 -> 8.3333333 | AG15: =AF15 -> 8.3333333 | AH15: =AG15 -> 8.3333333 | ... AK15: =AJ15 -> 8.3333333 | AL15: =Premissas!E31 -> 45.833333 | AM15: =AL15 -> 45.833333 | AN15: =AM15 -> 45.833333 | AO15: =AN15 -> 45.833333 | AP15: =AO15 -> 45.833333 | AQ15: =AP15 -> 45.833333 | AR15: =AQ15 -> 45.833333 | AS15: =AR15 -> 45.833333 | AT15: =AS15 -> 45.833333 | ... AW15: =AV15 -> 45.833333 | AX15: =Premissas!F31 -> 30.833333 | AY15: =AX15 -> 30.833333 | AZ15: =AY15 -> 30.833333 | BA15: =AZ15 -> 30.833333 | BB15: =BA15 -> 30.833333 | BC15: =BB15 -> 30.833333 | BD15: =BC15 -> 30.833333 | BE15: =BD15 -> 30.833333 | BF15: =BE15 -> 30.833333 | ... BI15: =BH15 -> 30.833333
A19: Receita Total | B19: =B6+B14 -> 4875 | C19: =C6+C14 -> 4875 | D19: =D6+D14 -> 4875 | E19: =E6+E14 -> 4875 | F19: =F6+F14 -> 4875 | G19: =G6+G14 -> 4875 | H19: =H6+H14 -> 4875 | I19: =I6+I14 -> 4875 | ... BI19: =BI6+BI14 -> 8812.5
A21: RESULTADOS ANUAIS | B21: Ano 1 | C21: Ano 2 | D21: Ano 3 | E21: Ano 4 | F21: Ano 5
A22: Vendas jogo 1 | B22: =SUM(B6:M6) -> 58500 | C22: =SUM(N5:Y5) -> 94791.667 | D22: =SUM(Z5:AK5) -> 67708.333 | E22: =SUM(AL5:AW5) -> 97500 | F22: =SUM(AX5:BI5) -> 78000
A23: Vendas Jogo 2 | B23: =SUM(B10:M10) -> 0 | C23: =SUM(N10:Y10) -> 0 | D23: =SUM(Z10:AK10) -> 0 | E23: =SUM(AL10:AW10) -> 220000 | F23: =SUM(AX10:BI10) -> 137500
A24: Venda assinatura | B24: =SUM(B14:M14) -> 0 | C24: =SUM(N14:Y14) -> 11250 | D24: =SUM(Z14:AK14) -> 7500 | E24: =SUM(AL14:AW14) -> 41250 | F24: =SUM(AX14:BI14) -> 27750
A25: RECEITA TOTAL | B25: =SUM(B22:B24) -> 58500 | C25: =SUM(C22:C24) -> 106041.67 | D25: =SUM(D22:D24) -> 75208.333 | E25: =SUM(E22:E24) -> 358750 | F25: =SUM(F22:F24) -> 243250
A54: ano 1
A55: ano 2
A56: ano 3
A57: ano 4 e 5

Sheet Investimentos_infra
A1: Investimentos
A2: =CONCATENATE(Company, ": ",start, " - ",end) -> Histyle: Mês 1 - Mês 60
A4: Investimentos em infraestrutura | B4: 1 | C4: 2 | D4: 3 | E4: 4 | F4: 5 | G4: 6 | H4: 7 | I4: 8 | J4: 9 | K4: 10 | L4: 11 | M4: 12 | N4: 13 | O4: 14 | P4: 15 | Q4: 16 | R4: 17 | S4: 18 | T4: 19 | U4: 20 | V4: 21 | W4: 22 | X4: 23 | Y4: 24 | Z4: 25 | AA4: 26 | AB4: 27 | AC4: 28 | AD4: 29 | AE4: 30 | AF4: 31 | AG4: 32 | AH4: 33 | AI4: 34 | AJ4: 35 | AK4: 36 | AL4: 37 | AM4: 38 | AN4: 39 | AO4: 40 | AP4: 41 | AQ4: 42 | AR4: 43 | AS4: 44 | AT4: 45 | AU4: 46 | AV4: 47 | AW4: 48 | AX4: 49 | AY4: 50 | AZ4: 51 | BA4: 52 | BB4: 53 | BC4: 54 | BD4: 55 | BE4: 56 | BF4: 57 | BG4: 58 | BH4: 59 | BI4: 60
A5: Computadores e manutenção deles | B5: =2000*Funcionários!B64 -> 6000 | C5: 0 | D5: 0 | E5: 0 | F5: 0 | G5: 0 | H5: 0 | I5: 0 | J5: 0 | K5: 0 | L5: 0 | M5: 0 | N5: =B5*0.2+(2000*(Funcionários!C64-Funcionários!B64)) -> 1200 | O5: 0 | P5: 0 | Q5: 0 | R5: 0 | S5: 0 | T5: 0 | U5: 0 | V5: 0 | W5: 0 | X5: 0 | Y5: 0 | Z5: =2000*Funcionários!C64*0.2+(2000*(Funcionários!D64-Funcionários!C64)) -> 1200 | AA5: 0 | AB5: 0 | AC5: 0 | AD5: 0 | AE5: 0 | AF5: 0 | AG5: 0 | AH5: 0 | AI5: 0 | AJ5: 0 | AK5: 0 | AL5: =2000*Funcionários!D64*0.2+(2000*(Funcionários!E64-Funcionários!D64)) -> 3200 | AM5: 0 | AN5: 0 | AO5: 0 | AP5: 0 | AQ5: 0 | AR5: 0 | AS5: 0 | AT5: 0 | AU5: 0 | AV5: 0 | AW5: 0 | AX5: =2000*Funcionários!E64*0.2+(2000*(Funcionários!F64-Funcionários!E64)) -> 3600 | AY5: 0 | AZ5: 0 | BA5: 0 | BB5: 0 | BC5: 0 | BD5: 0 | BE5: 0 | BF5: 0 | BG5: 0 | BH5: 0 | BI5: 0
A6: TOTAL | B6: =SUM(B5) -> 6000 | C6: =SUM(C5) -> 0 | D6: =SUM(D5) -> 0 | E6: =SUM(E5) -> 0 | F6: =SUM(F5) -> 0 | G6: =SUM(G5) -> 0 | H6: =SUM(H5) -> 0 | I6: =SUM(I5) -> 0 | ... BI6: =SUM(BI5) -> 0
A8: Investimentos em infraestrutura | B8: Ano 1 | C8: Ano 2 | D8: Ano 3 | E8: Ano 4 | F8: Ano 5
A9: Computadores e manutenção deles | B9: =SUM(B5:M5) -> 6000 | C9: =SUM(N5:Y5) -> 1200 | D9: =SUM( Z5:AK5) -> 1200 | E9: =SUM(AL5:AW5) -> 3200 | F9: =SUM(AX5:BI5) -> 3600
A10: TOTAL | B10: =SUM(B9) -> 6000 | C10: =SUM(C9) -> 1200 | D10: =SUM(D9) -> 1200 | E10: =SUM(E9) -> 3200 | F10: =SUM(F9) -> 3600

Sheet Despesas
A1: Despesas
A2: =CONCATENATE(Company, ": ",start, " - ",end) -> Histyle: Mês 1 - Mês 60
A3: Despesas operacionais | B3: 1 | C3: 2 | D3: 3 | E3: 4 | F3: 5 | G3: 6 | H3: 7 | I3: 8 | J3: 9 | K3: 10 | L3: 11 | M3: 12 | N3: 13 | O3: 14 | P3: 15 | Q3: 16 | R3: 17 | S3: 18 | T3: 19 | U3: 20 | V3: 21 | W3: 22 | X3: 23 | Y3: 24 | Z3: 25 | AA3: 26 | AB3: 27 | AC3: 28 | AD3: 29 | AE3: 30 | AF3: 31 | AG3: 32 | AH3: 33 | AI3: 34 | AJ3: 35 | AK3: 36 | AL3: 37 | AM3: 38 | AN3: 39 | AO3: 40 | AP3: 41 | AQ3: 42 | AR3: 43 | AS3: 44 | AT3: 45 | AU3: 46 | AV3: 47 | AW3: 48 | AX3: 49 | AY3: 50 | AZ3: 51 | BA3: 52 | BB3: 53 | BC3: 54 | BD3: 55 | BE3: 56 | BF3: 57 | BG3: 58 | BH3: 59 | BI3: 60
A4: Telefonia, energia elétrica e demais itens de telecomunicações | B4: 130 | C4: =B4 -> 130 | D4: =C4 -> 130 | E4: =D4 -> 130 | F4: =E4 -> 130 | G4: =F4 -> 130 | H4: =G4 -> 130 | I4: =H4 -> 130 | J4: =I4 -> 130 | ... M4: =L4 -> 130 | N4: =M4*1.06 -> 137.8 | O4: =N4 -> 137.8 | P4: =O4 -> 137.8 | Q4: =P4 -> 137.8 | R4: =Q4 -> 137.8 | S4: =R4 -> 137.8 | T4: =S4 -> 137.8 | U4: =T4 -> 137.8 | V4: =U4 -> 137.8 | ... Y4: =X4 -> 137.8 | Z4: =Y4*1.06 -> 146.068 | AA4: =Z4 -> 146.068 | AB4: =AA4 -> 146.068 | AC4: =AB4 -> 146.068 | AD4: =AC4 -> 146.068 | AE4: =AD4 -> 146.068 | AF4: =AE4 -> 146.068 | AG4: =AF4 -> 146.068 | AH4: =AG4 -> 146.068 | ... AK4: =AJ4 -> 146.068 | AL4: =AK4*1.06 -> 154.83208 | AM4: =AL4 -> 154.83208 | AN4: =AM4 -> 154.83208 | AO4: =AN4 -> 154.83208 | AP4: =AO4 -> 154.83208 | AQ4: =AP4 -> 154.83208 | AR4: =AQ4 -> 154.83208 | AS4: =AR4 -> 154.83208 | AT4: =AS4 -> 154.83208 | ... AW4: =AV4 -> 154.83208 | AX4: =AW4*1.06 -> 164.122 | AY4: =AX4 -> 164.122 | AZ4: =AY4 -> 164.122 | BA4: =AZ4 -> 164.122 | BB4: =BA4 -> 164.122 | BC4: =BB4 -> 164.122 | BD4: =BC4 -> 164.122 | BE4: =BD4 -> 164.122 | BF4: =BE4 -> 164.122 | ... BI4: =BH4 -> 164.122
A5: Registro de marca | B5: 655 | C5: 0 | D5: =C5 -> 0 | E5: =D5 -> 0 | F5: =E5 -> 0 | G5: =F5 -> 0 | H5: =G5 -> 0 | I5: =H5 -> 0 | J5: =I5 -> 0 | K5: =J5 -> 0 | ... M5: =L5 -> 0 | N5: =M5*1.06 -> 0 | O5: =N5 -> 0 | P5: =O5 -> 0 | Q5: =P5 -> 0 | R5: =Q5 -> 0 | S5: =R5 -> 0 | T5: =S5 -> 0 | U5: =T5 -> 0 | V5: =U5 -> 0 | ... Y5: =X5 -> 0 | Z5: =Y5*1.06 -> 0 | AA5: =Z5 -> 0 | AB5: =AA5 -> 0 | AC5: =AB5 -> 0 | AD5: =AC5 -> 0 | AE5: =AD5 -> 0 | AF5: =AE5 -> 0 | AG5: =AF5 -> 0 | AH5: =AG5 -> 0 | ... AK5: =AJ5 -> 0 | AL5: =AK5*1.06 -> 0 | AM5: =AL5 -> 0 | AN5: =AM5 -> 0 | AO5: =AN5 -> 0 | AP5: =AO5 -> 0 | AQ5: =AP5 -> 0 | AR5: =AQ5 -> 0 | AS5: =AR5 -> 0 | AT5: =AS5 -> 0 | ... AW5: =AV5 -> 0 | AX5: 0 | AY5: =AX5 -> 0 | AZ5: =AY5 -> 0 | BA5: =AZ5 -> 0 | BB5: =BA5 -> 0 | BC5: =BB5 -> 0 | BD5: =BC5 -> 0 | BE5: =BD5 -> 0 | BF5: =BE5 -> 0 | ... BI5: =BH5 -> 0
A6: Internet | B6: 120 | C6: =B6 -> 120 | D6: =C6 -> 120 | E6: =D6 -> 120 | F6: =E6 -> 120 | G6: =F6 -> 120 | H6: =G6 -> 120 | I6: =H6 -> 120 | J6: =I6 -> 120 | ... M6: =L6 -> 120 | N6: =(M6*1.06) -> 127.2 | O6: =N6 -> 127.2 | P6: =O6 -> 127.2 | Q6: =P6 -> 127.2 | R6: =Q6 -> 127.2 | S6: =R6 -> 127.2 | T6: =S6 -> 127.2 | U6: =T6 -> 127.2 | V6: =U6 -> 127.2 | ... Y6: =X6 -> 127.2 | Z6: =Y6*1.06 -> 134.832 | AA6: =Z6 -> 134.832 | AB6: =AA6 -> 134.832 | AC6: =AB6 -> 134.832 | AD6: =AC6 -> 134.832 | AE6: =AD6 -> 134.832 | AF6: =AE6 -> 134.832 | AG6: =AF6 -> 134.832 | AH6: =AG6 -> 134.832 | ... AK6: =AJ6 -> 134.832 | AL6: =(AK6*1.06)+(120*(Funcionários!E64-Funcionários!D64)) -> 262.92192 | AM6: =AL6 -> 262.92192 | AN6: =AM6 -> 262.92192 | AO6: =AN6 -> 262.92192 | AP6: =AO6 -> 262.92192 | AQ6: =AP6 -> 262.92192 | AR6: =AQ6 -> 262.92192 | AS6: =AR6 -> 262.92192 | AT6: =AS6 -> 262.92192 | ... AW6: =AV6 -> 262.92192 | AX6: =(AW6*1.06)+(120*(Funcionários!E64-Funcionários!D64)) -> 398.69724 | AY6: =AX6 -> 398.69724 | AZ6: =AY6 -> 398.69724 | BA6: =AZ6 -> 398.69724 | BB6: =BA6 -> 398.69724 | BC6: =BB6 -> 398.69724 | BD6: =BC6 -> 398.69724 | BE6: =BD6 -> 398.69724 | BF6: =BE6 -> 398.69724 | ... BI6: =BH6 -> 398.69724
A7: Treinamento e desenvovimento de equipe | B7: =750*Funcionários!B64 -> 2250 | C7: 0 | D7: =C7 -> 0 | E7: =D7 -> 0 | F7: =E7 -> 0 | G7: =F7 -> 0 | H7: =G7 -> 0 | I7: =H7 -> 0 | J7: =I7 -> 0 | K7: =J7 -> 0 | ... M7: =L7 -> 0 | N7: =750*Funcionários!C64 -> 2250 | O7: 0 | P7: 0 | Q7: 0 | R7: 0 | S7: 0 | T7: 0 | U7: 0 | V7: 0 | W7: 0 | X7: 0 | Y7: 0 | Z7: =750*Funcionários!D64 -> 2250 | AA7: 0 | AB7: 0 | AC7: 0 | AD7: 0 | AE7: 0 | AF7: 0 | AG7: 0 | AH7: 0 | AI7: 0 | AJ7: 0 | AK7: 0 | AL7: =750*Funcionários!E64 -> 3000 | AM7: 0 | AN7: 0 | AO7: 0 | AP7: 0 | AQ7: 0 | AR7: 0 | AS7: 0 | AT7: 0 | AU7: 0 | AV7: 0 | AW7: 0 | AX7: =750*Funcionários!F64 -> 3750 | AY7: 0 | AZ7: 0 | BA7: 0 | BB7: 0 | BC7: 0 | BD7: 0 | BE7: 0 | BF7: 0 | BG7: 0 | BH7: 0 | BI7: 0 | BJ7: 0
A8: Plano de saúdo para funcionários | B8: =100*Funcionários!B64 -> 300 | C8: =B8 -> 300 | D8: =C8 -> 300 | E8: =D8 -> 300 | F8: =E8 -> 300 | G8: =F8 -> 300 | H8: =G8 -> 300 | I8: =H8 -> 300 | J8: =I8 -> 300 | ... M8: =L8 -> 300 | N8: =100*Funcionários!C64 -> 300 | O8: =N8 -> 300 | P8: =O8 -> 300 | Q8: =P8 -> 300 | R8: =Q8 -> 300 | S8: =R8 -> 300 | T8: =S8 -> 300 | U8: =T8 -> 300 | V8: =U8 -> 300 | ... Y8: =X8 -> 300 | Z8: =100*Funcionários!D64 -> 300 | AA8: =Z8 -> 300 | AB8: =AA8 -> 300 | AC8: =AB8 -> 300 | AD8: =AC8 -> 300 | AE8: =AD8 -> 300 | AF8: =AE8 -> 300 | AG8: =AF8 -> 300 | AH8: =AG8 -> 300 | ... AK8: =AJ8 -> 300 | AL8: =100*Funcionários!E64 -> 400 | AM8: =AL8 -> 400 | AN8: =AM8 -> 400 | AO8: =AN8 -> 400 | AP8: =AO8 -> 400 | AQ8: =AP8 -> 400 | AR8: =AQ8 -> 400 | AS8: =AR8 -> 400 | AT8: =AS8 -> 400 | ... AW8: =AV8 -> 400 | AX8: =100*Funcionários!F64 -> 500 | AY8: =AX8 -> 500 | AZ8: =AY8 -> 500 | BA8: =AZ8 -> 500 | BB8: =BA8 -> 500 | BC8: =BB8 -> 500 | BD8: =BC8 -> 500 | BE8: =BD8 -> 500 | BF8: =BE8 -> 500 | ... BI8: =BH8 -> 500
A9: Contador | B9: 150 | C9: =B9 -> 150 | D9: =C9 -> 150 | E9: =D9 -> 150 | F9: =E9 -> 150 | G9: =F9 -> 150 | H9: =G9 -> 150 | I9: =H9 -> 150 | J9: =I9 -> 150 | ... M9: =L9 -> 150 | N9: =M9*1.06 -> 159 | O9: =N9 -> 159 | P9: =O9 -> 159 | Q9: =P9 -> 159 | R9: =Q9 -> 159 | S9: =R9 -> 159 | T9: =S9 -> 159 | U9: =T9 -> 159 | V9: =U9 -> 159 | ... Y9: =X9 -> 159 | Z9: =Y9*1.06 -> 168.54 | AA9: =Z9 -> 168.54 | AB9: =AA9 -> 168.54 | AC9: =AB9 -> 168.54 | AD9: =AC9 -> 168.54 | AE9: =AD9 -> 168.54 | AF9: =AE9 -> 168.54 | AG9: =AF9 -> 168.54 | AH9: =AG9 -> 168.54 | ... AK9: =AJ9 -> 168.54 | AL9: =AK9*1.06 -> 178.6524 | AM9: =AL9 -> 178.6524 | AN9: =AM9 -> 178.6524 | AO9: =AN9 -> 178.6524 | AP9: =AO9 -> 178.6524 | AQ9: =AP9 -> 178.6524 | AR9: =AQ9 -> 178.6524 | AS9: =AR9 -> 178.6524 | AT9: =AS9 -> 178.6524 | ... AW9: =AV9 -> 178.6524 | AX9: =AW9*1.06 -> 189.37154 | AY9: =AX9 -> 189.37154 | AZ9: =AY9 -> 189.37154 | BA9: =AZ9 -> 189.37154 | BB9: =BA9 -> 189.37154 | BC9: =BB9 -> 189.37154 | BD9: =BC9 -> 189.37154 | BE9: =BD9 -> 189.37154 | BF9: =BE9 -> 189.37154 | ... BI9: =BH9 -> 189.37154
A10: TOTAL | B10: =SUM(B4:B9) -> 3605 | C10: =SUM(C4:C9) -> 700 | D10: =SUM(D4:D9) -> 700 | E10: =SUM(E4:E9) -> 700 | F10: =SUM(F4:F9) -> 700 | G10: =SUM(G4:G9) -> 700 | H10: =SUM(H4:H9) -> 700 | I10: =SUM(I4:I9) -> 700 | ... BI10: =SUM(BI4:BI9) -> 1252.1908
A20: Despesas operacionais | B20: Ano 1 | C20: Ano 2 | D20: Ano 3 | E20: Ano 4 | F20: Ano 5
A21: Telefonia, energia elétrica e demais itens de telecomunicações | B21: =SUM(B4:M4) -> 1560 | C21: =SUM(N4:Y4) -> 1653.6 | D21: =SUM(Z4:AK4) -> 1752.816 | E21: =SUM(AL4:AW4) -> 1857.985 | F21: =SUM(AX4:BI4) -> 1969.4641
A22: Internet | B22: =SUM(B6:M6) -> 1440 | C22: =SUM(N6:Y6) -> 1526.4 | D22: =SUM(Z6:AK6) -> 1617.984 | E22: =SUM(AL6:AW6) -> 3155.063 | F22: =SUM(AX6:BI6) -> 4784.3668
A23: Treinamento e desenvovimento de equipe | B23: =SUM(B7:M7) -> 2250 | C23: =SUM(N7:Y7) -> 2250 | D23: =SUM(Z7:AK7) -> 2250 | E23: =SUM(AL7:AW7) -> 3000 | F23: =SUM(AX7:BI7) -> 3750
A24: Plano de saúdo para funcionários | B24: =SUM(B8:M8) -> 3600 | C24: =SUM(N8:Y8) -> 3600 | D24: =SUM(Z8:AK8) -> 3600 | E24: =SUM(AL8:AW8) -> 4800 | F24: =SUM(AX8:BI8) -> 6000
A25: Contador | B25: =SUM(B9:M9) -> 1800 | C25: =SUM(N9:Y9) -> 1908 | D25: =SUM(Z9:AK9) -> 2022.48 | E25: =SUM(AL9:AW9) -> 2143.8288 | F25: =SUM(AX9:BI9) -> 2272.4585
A26: TOTAL | B26: =SUM(B21:B25) -> 10650 | C26: =SUM(C21:C25) -> 10938 | D26: =SUM(D21:D25) -> 11243.28 | E26: =SUM(E21:E25) -> 14956.877 | F26: =SUM(F21:F25) -> 18776.289

Sheet Custos
A1: Custos
A2: =CONCATENATE(Company, ": ",start, " - ",end) -> Histyle: Mês 1 - Mês 60
A4: Custos | B4: 1 | C4: 2 | D4: 3 | E4: 4 | F4: 5 | G4: 6 | H4: 7 | I4: 8 | J4: 9 | K4: 10 | L4: 11 | M4: 12 | N4: 13 | O4: 14 | P4: 15 | Q4: 16 | R4: 17 | S4: 18 | T4: 19 | U4: 20 | V4: 21 | W4: 22 | X4: 23 | Y4: 24 | Z4: 25 | AA4: 26 | AB4: 27 | AC4: 28 | AD4: 29 | AE4: 30 | AF4: 31 | AG4: 32 | AH4: 33 | AI4: 34 | AJ4: 35 | AK4: 36 | AL4: 37 | AM4: 38 | AN4: 39 | AO4: 40 | AP4: 41 | AQ4: 42 | AR4: 43 | AS4: 44 | AT4: 45 | AU4: 46 | AV4: 47 | AW4: 48 | AX4: 49 | AY4: 50 | AZ4: 51 | BA4: 52 | BB4: 53 | BC4: 54 | BD4: 55 | BE4: 56 | BF4: 57 | BG4: 58 | BH4: 59 | BI4: 60
A5: Hospedagem do website | B5: 20 | C5: =B5 -> 20 | D5: =C5 -> 20 | E5: =D5 -> 20 | F5: =E5 -> 20 | G5: =F5 -> 20 | H5: =G5 -> 20 | I5: =H5 -> 20 | J5: =I5 -> 20 | ... M5: =L5 -> 20 | N5: =M5*1.06 -> 21.2 | O5: =N5 -> 21.2 | P5: =O5 -> 21.2 | Q5: =P5 -> 21.2 | R5: =Q5 -> 21.2 | S5: =R5 -> 21.2 | T5: =S5 -> 21.2 | U5: =T5 -> 21.2 | V5: =U5 -> 21.2 | ... Y5: =X5 -> 21.2 | Z5: =Y5*1.06 -> 22.472 | AA5: =Z5 -> 22.472 | AB5: =AA5 -> 22.472 | AC5: =AB5 -> 22.472 | AD5: =AC5 -> 22.472 | AE5: =AD5 -> 22.472 | AF5: =AE5 -> 22.472 | AG5: =AF5 -> 22.472 | AH5: =AG5 -> 22.472 | ... AK5: =AJ5 -> 22.472 | AL5: =AK5*1.06 -> 23.82032 | AM5: =AL5 -> 23.82032 | AN5: =AM5 -> 23.82032 | AO5: =AN5 -> 23.82032 | AP5: =AO5 -> 23.82032 | AQ5: =AP5 -> 23.82032 | AR5: =AQ5 -> 23.82032 | AS5: =AR5 -> 23.82032 | AT5: =AS5 -> 23.82032 | ... AW5: =AV5 -> 23.82032 | AX5: =AW5*1.06 -> 25.249539 | AY5: =AX5 -> 25.249539 | AZ5: =AY5 -> 25.249539 | BA5: =AZ5 -> 25.249539 | BB5: =BA5 -> 25.249539 | BC5: =BB5 -> 25.249539 | BD5: =BC5 -> 25.249539 | BE5: =BD5 -> 25.249539 | BF5: =BE5 -> 25.249539 | ... BI5: =BH5 -> 25.249539
A6: Registro do jogo | B6: 655 | C6: 0 | D6: =C6 -> 0 | E6: =D6 -> 0 | F6: =E6 -> 0 | G6: =F6 -> 0 | H6: =G6 -> 0 | I6: =H6 -> 0 | J6: =I6 -> 0 | K6: =J6 -> 0 | ... M6: =L6 -> 0 | N6: =M6*1.06 -> 0 | O6: =N6 -> 0 | P6: =O6 -> 0 | Q6: =P6 -> 0 | R6: =Q6 -> 0 | S6: =R6 -> 0 | T6: =S6 -> 0 | U6: =T6 -> 0 | V6: =U6 -> 0 | ... Y6: =X6 -> 0 | Z6: =Y6*1.06 -> 0 | AA6: =Z6 -> 0 | AB6: =AA6 -> 0 | AC6: =AB6 -> 0 | AD6: =AC6 -> 0 | AE6: =AD6 -> 0 | AF6: =AE6 -> 0 | AG6: =AF6 -> 0 | AH6: =AG6 -> 0 | ... AK6: =AJ6 -> 0 | AL6: =AK6*1.06 -> 0 | AM6: =AL6 -> 0 | AN6: =AM6 -> 0 | AO6: =AN6 -> 0 | AP6: =AO6 -> 0 | AQ6: =AP6 -> 0 | AR6: =AQ6 -> 0 | AS6: =AR6 -> 0 | AT6: =AS6 -> 0 | ... AV6: =AU6 -> 0 | AW6: =655*(1.06^4) -> 826.92241 | AX6: 0 | AY6: =AX6 -> 0 | AZ6: =AY6 -> 0 | BA6: =AZ6 -> 0 | BB6: =BA6 -> 0 | BC6: =BB6 -> 0 | BD6: =BC6 -> 0 | BE6: =BD6 -> 0 | BF6: =BE6 -> 0 | ... BI6: =BH6 -> 0
A7: Adobe Premiere Pro | B7: =90*Funcionários!B64 -> 270 | C7: =B7 -> 270 | D7: =C7 -> 270 | E7: =D7 -> 270 | F7: =E7 -> 270 | G7: =F7 -> 270 | H7: =G7 -> 270 | I7: =H7 -> 270 | J7: =I7 -> 270 | ... M7: =L7 -> 270 | N7: =90*Funcionários!C64 -> 270 | O7: =N7 -> 270 | P7: =O7 -> 270 | Q7: =P7 -> 270 | R7: =Q7 -> 270 | S7: =R7 -> 270 | T7: =S7 -> 270 | U7: =T7 -> 270 | V7: =U7 -> 270 | ... Y7: =X7 -> 270 | Z7: =90*Funcionários!D64 -> 270 | AA7: =Z7 -> 270 | AB7: =AA7 -> 270 | AC7: =AB7 -> 270 | AD7: =AC7 -> 270 | AE7: =AD7 -> 270 | AF7: =AE7 -> 270 | AG7: =AF7 -> 270 | AH7: =AG7 -> 270 | ... AK7: =AJ7 -> 270 | AL7: =90*Funcionários!E64 -> 360 | AM7: =AL7 -> 360 | AN7: =AM7 -> 360 | AO7: =AN7 -> 360 | AP7: =AO7 -> 360 | AQ7: =AP7 -> 360 | AR7: =AQ7 -> 360 | AS7: =AR7 -> 360 | AT7: =AS7 -> 360 | ... AW7: =AV7 -> 360 | AX7: =90*Funcionários!F64 -> 450 | AY7: =AX7 -> 450 | AZ7: =AY7 -> 450 | BA7: =AZ7 -> 450 | BB7: =BA7 -> 450 | BC7: =BB7 -> 450 | BD7: =BC7 -> 450 | BE7: =BD7 -> 450 | BF7: =BE7 -> 450 | ... BI7: =BH7 -> 450
A8: TOTAL | B8: =SUM(B5:B7) -> 945 | C8: =SUM(C5:C7) -> 290 | D8: =SUM(D5:D7) -> 290 | E8: =SUM(E5:E7) -> 290 | F8: =SUM(F5:F7) -> 290 | G8: =SUM(G5:G7) -> 290 | H8: =SUM(H5:H7) -> 290 | I8: =SUM(I5:I7) -> 290 | ... BI8: =SUM(BI5:BI7) -> 475.24954
A11: Custos | B11: Ano 1 | C11: Ano 2 | D11: Ano 3 | E11: Ano 4 | F11: Ano 5
A12: Hospedagem do website | B12: =SUM(B5:M5) -> 240 | C12: =SUM(N5:Y5) -> 254.4 | D12: =SUM(Z5:AK5) -> 269.664 | E12: =SUM(AL5:AW5) -> 285.84384 | F12: =SUM(AX5:BI5) -> 302.99447
A13: Registro de jogo | B13: =SUM(B6:M6) -> 655 | C13: =SUM(N6:Y6) -> 0 | D13: =SUM(Z6:AK6) -> 0 | E13: =SUM(AL6:AW6) -> 826.92241 | F13: =SUM(AX6:BI6) -> 0
A14: Adobe Premiere Pro | B14: =SUM(B7:M7) -> 3240 | C14: =SUM(N7:Y7) -> 3240 | D14: =SUM(Z7:AK7) -> 3240 | E14: =SUM(AL7:AW7) -> 4320 | F14: =SUM(AX7:BI7) -> 5400
A15: TOTAL | B15: =SUM(B12:B13) -> 895 | C15: =SUM(C12:C13) -> 254.4 | D15: =SUM(D12:D13) -> 269.664 | E15: =SUM(E12:E13) -> 1112.7662 | F15: =SUM(F12:F13) -> 302.99447

Sheet Funcionários
A1: Salário dos Funcionários
A2: =CONCATENATE(Company, " : ",start, " - ",end) -> Histyle : Mês 1 - Mês 60
A3: =CONCATENATE("Valores em ",currency) -> Valores em R$
B6: mês1 | C6: mês 2 | D6: mês3 | E6: mês4 | F6: mês5 | G6: mês6 | H6: mês7 | I6: mês8 | J6: mês9 | K6: mês10 | L6: mês11 | M6: mês12 | N6: mês13 | O6: mês14 | P6: mês15 | Q6: mês16 | R6: mês17 | S6: mês18 | T6: mês19 | U6: mês20 | V6: mês21 | W6: mês22 | X6: mês23 | Y6: mês24 | Z6: mês25 | AA6: mês26 | AB6: mês27 | AC6: mês28 | AD6: mês29 | AE6: mês30 | AF6: mês31 | AG6: mês32 | AH6: mês33 | AI6: mês34 | AJ6: mês35 | AK6: mês36 | AL6: mês37 | AM6: mês38 | AN6: mês39 | AO6: mês40 | AP6: mês41 | AQ6: mês42 | AR6: mês43 | AS6: mês44 | AT6: mês45 | AU6: mês46 | AV6: mês47 | AW6: mês48 | AX6: mês49 | AY6: mês50 | AZ6: mês51 | BA6: mês52 | BB6: mês53 | BC6: mês54 | BD6: mês55 | BE6: mês56 | BF6: mês57 | BG6: mês58 | BH6: mês59 | BI6: mês60
A7: QUADRO DE FUNCIONÁRIOS
A8: CEO
A9: CEO | B9: 1 | C9: 1 | D9: 1 | E9: 1 | F9: =E9 -> 1 | G9: =F9 -> 1 | H9: =G9 -> 1 | I9: =H9 -> 1 | J9: =I9 -> 1 | K9: =J9 -> 1 | L9: =K9 -> 1 | M9: =L9 -> 1 | ... BI9: =BH9 -> 1
A10: OPERACIONAL
A11: DESENVOLVEDOR DE JOGOS | B11: 1 | C11: =B11 -> 1 | D11: =C11 -> 1 | E11: =D11 -> 1 | F11: =E11 -> 1 | G11: =F11 -> 1 | H11: =G11 -> 1 | I11: =H11 -> 1 | J11: =I11 -> 1 | ... AJ11: =AI11 -> 1 | AK11: 1 | AL11: =AK11 -> 1 | AM11: =AL11 -> 1 | AN11: =AM11 -> 1 | AO11: =AN11 -> 1 | AP11: =AO11 -> 1 | AQ11: =AP11 -> 1 | AR11: =AQ11 -> 1 | AS11: =AR11 -> 1 | ... BI11: =BH11 -> 1
A12: ARTISTA GRÁFICO | B12: 1 | C12: =B12 -> 1 | D12: =C12 -> 1 | E12: =D12 -> 1 | F12: =E12 -> 1 | G12: =F12 -> 1 | H12: =G12 -> 1 | I12: =H12 -> 1 | J12: =I12 -> 1 | ... AJ12: =AI12 -> 1 | AK12: 2 | AL12: =AK12 -> 2 | AM12: =AL12 -> 2 | AN12: =AM12 -> 2 | AO12: =AN12 -> 2 | AP12: =AO12 -> 2 | AQ12: =AP12 -> 2 | AR12: =AQ12 -> 2 | AS12: =AR12 -> 2 | ... BI12: =BH12 -> 2
A13: PROGRAMADOR | B13: 0 | C13: 0 | D13: 0 | E13: 0 | F13: 0 | G13: 0 | H13: 0 | I13: 0 | J13: 0 | K13: 0 | L13: 0 | M13: 0 | N13: 0 | O13: 0 | P13: 0 | Q13: 0 | R13: 0 | S13: 0 | T13: 0 | U13: 0 | V13: 0 | W13: 0 | X13: 0 | Y13: 0 | Z13: 0 | AA13: 0 | AB13: 0 | AC13: 0 | AD13: 0 | AE13: 0 | AF13: 0 | AG13: 0 | AH13: 0 | AI13: 0 | AJ13: 0 | AK13: 0 | AL13: 0 | AM13: 0 | AN13: 0 | AO13: 0 | AP13: 0 | AQ13: 0 | AR13: 0 | AS13: 0 | AT13: 0 | AU13: 0 | AV13: 0 | AW13: 1 | AX13: =AW13 -> 1 | AY13: =AX13 -> 1 | AZ13: =AY13 -> 1 | BA13: =AZ13 -> 1 | BB13: =BA13 -> 1 | BC13: =BB13 -> 1 | BD13: =BC13 -> 1 | BE13: =BD13 -> 1 | ... BI13: =BH13 -> 1
A15: SALÁRIOS (já com ENCARGOS/BENEFÍCIOS)
A16: CONSELHO
A17: CEO | B17: 2000 | C17: =B17 -> 2000 | D17: =C17 -> 2000 | E17: =D17 -> 2000 | F17: =E17 -> 2000 | G17: =F17 -> 2000 | H17: =G17 -> 2000 | I17: =H17 -> 2000 | J17: =I17 -> 2000 | ... M17: =L17 -> 2000 | N17: =M17*1.06 -> 2120 | O17: =N17 -> 2120 | P17: =O17 -> 2120 | Q17: =P17 -> 2120 | R17: =Q17 -> 2120 | S17: =R17 -> 2120 | T17: =S17 -> 2120 | U17: =T17 -> 2120 | V17: =U17 -> 2120 | ... Y17: =X17 -> 2120 | Z17: =Y17*1.06 -> 2247.2 | AA17: =Z17 -> 2247.2 | AB17: =AA17 -> 2247.2 | AC17: =AB17 -> 2247.2 | AD17: =AC17 -> 2247.2 | AE17: =AD17 -> 2247.2 | AF17: =AE17 -> 2247.2 | AG17: =AF17 -> 2247.2 | AH17: =AG17 -> 2247.2 | ... AK17: =AJ17 -> 2247.2 | AL17: =AK17*1.06 -> 2382.032 | AM17: =AL17 -> 2382.032 | AN17: =AM17 -> 2382.032 | AO17: =AN17 -> 2382.032 | AP17: =AO17 -> 2382.032 | AQ17: =AP17 -> 2382.032 | AR17: =AQ17 -> 2382.032 | AS17: =AR17 -> 2382.032 | AT17: =AS17 -> 2382.032 | ... AW17: =AV17 -> 2382.032 | AX17: =AW17*1.06 -> 2524.9539 | AY17: =AX17 -> 2524.9539 | AZ17: =AY17 -> 2524.9539 | BA17: =AZ17 -> 2524.9539 | BB17: =BA17 -> 2524.9539 | BC17: =BB17 -> 2524.9539 | BD17: =BC17 -> 2524.9539 | BE17: =BD17 -> 2524.9539 | BF17: =BE17 -> 2524.9539 | ... BI17: =BH17 -> 2524.9539
A18: =A10 -> OPERACIONAL | C18: =B18 -> 0 | D18: =C18 -> 0 | E18: =D18 -> 0 | F18: =E18 -> 0 | G18: =F18 -> 0 | H18: =G18 -> 0 | I18: =H18 -> 0 | J18: =I18 -> 0 | ... M18: =L18 -> 0 | N18: =M18*1.06 -> 0 | O18: =N18 -> 0 | P18: =O18 -> 0 | Q18: =P18 -> 0 | R18: =Q18 -> 0 | S18: =R18 -> 0 | T18: =S18 -> 0 | U18: =T18 -> 0 | V18: =U18 -> 0 | ... Y18: =X18 -> 0 | Z18: =Y18*1.06 -> 0 | AA18: =Z18 -> 0 | AB18: =AA18 -> 0 | AC18: =AB18 -> 0 | AD18: =AC18 -> 0 | AE18: =AD18 -> 0 | AF18: =AE18 -> 0 | AG18: =AF18 -> 0 | AH18: =AG18 -> 0 | ... AK18: =AJ18 -> 0 | AL18: =AK18*1.06 -> 0 | AM18: =AL18 -> 0 | AN18: =AM18 -> 0 | AO18: =AN18 -> 0 | AP18: =AO18 -> 0 | AQ18: =AP18 -> 0 | AR18: =AQ18 -> 0 | AS18: =AR18 -> 0 | AT18: =AS18 -> 0 | ... AW18: =AV18 -> 0 | AX18: =AW18*1.06 -> 0 | AY18: =AX18 -> 0 | AZ18: =AY18 -> 0 | BA18: =AZ18 -> 0 | BB18: =BA18 -> 0 | BC18: =BB18 -> 0 | BD18: =BC18 -> 0 | BE18: =BD18 -> 0 | BF18: =BE18 -> 0 | ... BI18: =BH18 -> 0
A19: =A11 -> DESENVOLVEDOR DE JOGOS | B19: 2000 | C19: =B19 -> 2000 | D19: =C19 -> 2000 | E19: =D19 -> 2000 | F19: =E19 -> 2000 | G19: =F19 -> 2000 | H19: =G19 -> 2000 | I19: =H19 -> 2000 | J19: =I19 -> 2000 | ... M19: =L19 -> 2000 | N19: =M19*1.06 -> 2120 | O19: =N19 -> 2120 | P19: =O19 -> 2120 | Q19: =P19 -> 2120 | R19: =Q19 -> 2120 | S19: =R19 -> 2120 | T19: =S19 -> 2120 | U19: =T19 -> 2120 | V19: =U19 -> 2120 | ... Y19: =X19 -> 2120 | Z19: =Y19*1.06 -> 2247.2 | AA19: =Z19 -> 2247.2 | AB19: =AA19 -> 2247.2 | AC19: =AB19 -> 2247.2 | AD19: =AC19 -> 2247.2 | AE19: =AD19 -> 2247.2 | AF19: =AE19 -> 2247.2 | AG19: =AF19 -> 2247.2 | AH19: =AG19 -> 2247.2 | ... AK19: =AJ19 -> 2247.2 | AL19: =AK19*1.06 -> 2382.032 | AM19: =AL19 -> 2382.032 | AN19: =AM19 -> 2382.032 | AO19: =AN19 -> 2382.032 | AP19: =AO19 -> 2382.032 | AQ19: =AP19 -> 2382.032 | AR19: =AQ19 -> 2382.032 | AS19: =AR19 -> 2382.032 | AT19: =AS19 -> 2382.032 | ... AW19: =AV19 -> 2382.032 | AX19: =AW19*1.06 -> 2524.9539 | AY19: =AX19 -> 2524.9539 | AZ19: =AY19 -> 2524.9539 | BA19: =AZ19 -> 2524.9539 | BB19: =BA19 -> 2524.9539 | BC19: =BB19 -> 2524.9539 | BD19: =BC19 -> 2524.9539 | BE19: =BD19 -> 2524.9539 | BF19: =BE19 -> 2524.9539 | ... BI19: =BH19 -> 2524.9539
A20: =A12 -> ARTISTA GRÁFICO | B20: 2000 | C20: =B20 -> 2000 | D20: =C20 -> 2000 | E20: =D20 -> 2000 | F20: =E20 -> 2000 | G20: =F20 -> 2000 | H20: =G20 -> 2000 | I20: =H20 -> 2000 | J20: =I20 -> 2000 | ... M20: =L20 -> 2000 | N20: =M20*1.06 -> 2120 | O20: =N20 -> 2120 | P20: =O20 -> 2120 | Q20: =P20 -> 2120 | R20: =Q20 -> 2120 | S20: =R20 -> 2120 | T20: =S20 -> 2120 | U20: =T20 -> 2120 | V20: =U20 -> 2120 | ... Y20: =X20 -> 2120 | Z20: =Y20*1.06 -> 2247.2 | AA20: =Z20 -> 2247.2 | AB20: =AA20 -> 2247.2 | AC20: =AB20 -> 2247.2 | AD20: =AC20 -> 2247.2 | AE20: =AD20 -> 2247.2 | AF20: =AE20 -> 2247.2 | AG20: =AF20 -> 2247.2 | AH20: =AG20 -> 2247.2 | ... AK20: =AJ20 -> 2247.2 | AL20: =AK20*1.06 -> 2382.032 | AM20: =AL20 -> 2382.032 | AN20: =AM20 -> 2382.032 | AO20: =AN20 -> 2382.032 | AP20: =AO20 -> 2382.032 | AQ20: =AP20 -> 2382.032 | AR20: =AQ20 -> 2382.032 | AS20: =AR20 -> 2382.032 | AT20: =AS20 -> 2382.032 | ... AW20: =AV20 -> 2382.032 | AX20: =AW20*1.06 -> 2524.9539 | AY20: =AX20 -> 2524.9539 | AZ20: =AY20 -> 2524.9539 | BA20: =AZ20 -> 2524.9539 | BB20: =BA20 -> 2524.9539 | BC20: =BB20 -> 2524.9539 | BD20: =BC20 -> 2524.9539 | BE20: =BD20 -> 2524.9539 | BF20: =BE20 -> 2524.9539 | ... BI20: =BH20 -> 2524.9539
A21: PROGRAMADOR | B21: 2000 | C21: =B21 -> 2000 | D21: =C21 -> 2000 | E21: =D21 -> 2000 | F21: =E21 -> 2000 | G21: =F21 -> 2000 | H21: =G21 -> 2000 | I21: =H21 -> 2000 | J21: =I21 -> 2000 | ... M21: =L21 -> 2000 | N21: =M21*1.06 -> 2120 | O21: =N21 -> 2120 | P21: =O21 -> 2120 | Q21: =P21 -> 2120 | R21: =Q21 -> 2120 | S21: =R21 -> 2120 | T21: =S21 -> 2120 | U21: =T21 -> 2120 | V21: =U21 -> 2120 | ... Y21: =X21 -> 2120 | Z21: =Y21*1.06 -> 2247.2 | AA21: =Z21 -> 2247.2 | AB21: =AA21 -> 2247.2 | AC21: =AB21 -> 2247.2 | AD21: =AC21 -> 2247.2 | AE21: =AD21 -> 2247.2 | AF21: =AE21 -> 2247.2 | AG21: =AF21 -> 2247.2 | AH21: =AG21 -> 2247.2 | ... AK21: =AJ21 -> 2247.2 | AL21: =AK21*1.06 -> 2382.032 | AM21: =AL21 -> 2382.032 | AN21: =AM21 -> 2382.032 | AO21: =AN21 -> 2382.032 | AP21: =AO21 -> 2382.032 | AQ21: =AP21 -> 2382.032 | AR21: =AQ21 -> 2382.032 | AS21: =AR21 -> 2382.032 | AT21: =AS21 -> 2382.032 | ... AW21: =AV21 -> 2382.032 | AX21: =AW21*1.06 -> 2524.9539 | AY21: =AX21 -> 2524.9539 | AZ21: =AY21 -> 2524.9539 | BA21: =AZ21 -> 2524.9539 | BB21: =BA21 -> 2524.9539 | BC21: =BB21 -> 2524.9539 | BD21: =BC21 -> 2524.9539 | BE21: =BD21 -> 2524.9539 | BF21: =BE21 -> 2524.9539 | ... BI21: =BH21 -> 2524.9539
A23: GASTOS TOTAIS COM SALÁRIOS/BENEFÍCIOS
A24: CONSELHO | B24: =B16*B8 -> 0 | C24: =C16*C8 -> 0 | D24: =D16*D8 -> 0 | E24: =E16*E8 -> 0 | F24: =F16*F8 -> 0 | G24: =G16*G8 -> 0 | H24: =H16*H8 -> 0 | I24: =I16*I8 -> 0 | ... BI24: =BI16*BI8 -> 0
A25: CEO | B25: =B17*B9 -> 2000 | C25: =C17*C9 -> 2000 | D25: =D17*D9 -> 2000 | E25: =E17*E9 -> 2000 | F25: =F17*F9 -> 2000 | G25: =G17*G9 -> 2000 | H25: =H17*H9 -> 2000 | I25: =I17*I9 -> 2000 | ... N25: =N17*N9 -> 2120 | O25: =N17*O9 -> 2120 | P25: =P17*P9 -> 2120 | Q25: =Q17*Q9 -> 2120 | R25: =R17*R9 -> 2120 | S25: =S17*S9 -> 2120 | T25: =T17*T9 -> 2120 | U25: =U17*U9 -> 2120 | V25: =V17*V9 -> 2120 | W25: =W17*W9 -> 2120 | ... BI25: =BI17*BI9 -> 2524.9539
A26: =A10 -> OPERACIONAL | B26: =B18*B10 -> 0 | C26: =C18*C10 -> 0 | D26: =D18*D10 -> 0 | E26: =E18*E10 -> 0 | F26: =F18*F10 -> 0 | G26: =G18*G10 -> 0 | H26: =H18*H10 -> 0 | I26: =I18*I10 -> 0 | ... BI26: =BI18*BI10 -> 0
A27: =A11 -> DESENVOLVEDOR DE JOGOS | B27: =B19*B11 -> 2000 | C27: =C19*C11 -> 2000 | D27: =D19*D11 -> 2000 | E27: =E19*E11 -> 2000 | F27: =F19*F11 -> 2000 | G27: =G19*G11 -> 2000 | H27: =H19*H11 -> 2000 | I27: =I19*I11 -> 2000 | ... BI27: =BI19*BI11 -> 2524.9539
A28: =A12 -> ARTISTA GRÁFICO | B28: =B20*B12 -> 2000 | C28: =C20*C12 -> 2000 | D28: =D20*D12 -> 2000 | E28: =E20*E12 -> 2000 | F28: =F20*F12 -> 2000 | G28: =G20*G12 -> 2000 | H28: =H20*H12 -> 2000 | I28: =I20*I12 -> 2000 | ... BI28: =BI20*BI12 -> 5049.9078
A29: =A13 -> PROGRAMADOR | B29: =B21*B13 -> 0 | C29: =C21*C13 -> 0 | D29: =D21*D13 -> 0 | E29: =E21*E13 -> 0 | F29: =F21*F13 -> 0 | G29: =G21*G13 -> 0 | H29: =H21*H13 -> 0 | I29: =I21*I13 -> 0 | ... BI29: =BI21*BI13 -> 2524.9539
A31: GASTOS TOTAIS COM FUNCIONÁRIOS | B31: =SUM(B24:B30) -> 6000 | C31: =SUM(C24:C30) -> 6000 | D31: =SUM(D24:D30) -> 6000 | E31: =SUM(E24:E30) -> 6000 | F31: =SUM(F24:F30) -> 6000 | G31: =SUM(G24:G30) -> 6000 | H31: =SUM(H24:H30) -> 6000 | I31: =SUM(I24:I30) -> 6000 | ... BI31: =SUM(BI24:BI30) -> 12624.77
A33: GASTOS TOTAIS COM SALÁRIOS/BENEFÍCIOS | B33: Ano 1 | C33: Ano 2 | D33: Ano 3 | E33: Ano 4 | F33: Ano 5
A34: CEO | B34: =SUM(B25:M25) -> 24000 | C34: =SUM(N25:Y25) -> 25440 | D34: =SUM(Z25:AK25) -> 26966.4 | E34: =SUM(AL25:AW25) -> 28584.384 | F34: =SUM(AX25:BI25) -> 30299.447
A35: Desenvolvedor de jogos | B35: =SUM(B27:M27) -> 24000 | C35: =SUM(N27:Y27) -> 25440 | D35: =SUM(Z27:AK27) -> 26966.4 | E35: =SUM(AL27:AW27) -> 28584.384 | F35: =SUM(AX27:BI27) -> 30299.447
A36: Artista gráfico | B36: =SUM(B28:M28) -> 24000 | C36: =SUM(N28:Y28) -> 25440 | D36: =SUM(Z28:AK28) -> 29213.6 | E36: =SUM(AL28:AW28) -> 57168.768 | F36: =SUM(AX28:BI28) -> 60598.894
A37: Programador | B37: =SUM(B29:M29) -> 0 | C37: =SUM(N29:Y29) -> 0 | D37: =SUM(Z29:AK29) -> 0 | E37: =SUM(AL29:AW29) -> 2382.032 | F37: =SUM(AX29:BI29) -> 30299.447
A38: GASTOS TOTAIS COM FUNCIONÁRIOS | B38: =SUM(B34:B37) -> 72000 | C38: =SUM(C34:C37) -> 76320 | D38: =SUM(D34:D37) -> 83146.4 | E38: =SUM(E34:E37) -> 116719.57 | F38: =SUM(F34:F37) -> 151497.24 | G38: 4367.4885
G39: 5149.4541
A40: QUANTIDADE DE FUNCIONÁRIOS | B40: Ano 1 | C40: Ano 2 | D40: Ano 3 | E40: Ano 4 | F40: Ano 5 | G40: 2802.762
A41: CEO | B41: =B9 -> 1 | C41: =N9 -> 1 | D41: =Z9 -> 1 | E41: =AL9 -> 1 | F41: =AX9 -> 1
A42: Desenvolvedor de jogos | B42: =B11 -> 1 | C42: =N11 -> 1 | D42: =Z11 -> 1 | E42: =AL11 -> 1 | F42: =AX11 -> 1
A43: Artista gráfico | B43: =B12 -> 1 | C43: =N12 -> 1 | D43: =Z12 -> 1 | E43: =AL12 -> 2 | F43: =AX12 -> 2
A44: Programador | B44: =B13 -> 0 | C44: =N13 -> 0 | D44: =Z13 -> 0 | E44: =AL13 -> 0 | F44: =AX13 -> 1
A45: TOTAL DE FUNCIONÁRIOS | B45: =SUM(B42:B44) -> 2 | C45: =SUM(C42:C44) -> 2 | D45: =SUM(D42:D44) -> 2 | E45: =SUM(E42:E44) -> 3 | F45: =SUM(F42:F44) -> 4
A64: TOTAL DE FUNCIONÁRIOS + CEO | B64: =SUM(B41:B44) -> 3 | C64: =SUM(C41:C44) -> 3 | D64: =SUM(D41:D44) -> 3 | E64: =SUM(E41:E44) -> 4 | F64: =SUM(F41:F44) -> 5

Sheet Resultados
A1: Resultados
A2: =CONCATENATE(Company, ": ",start, " - ",end) -> Histyle: Mês 1 - Mês 60
A4: Receita | B4: 1 | C4: 2 | D4: 3 | E4: 4 | F4: 5 | G4: 6 | H4: 7 | I4: 8 | J4: 9 | K4: 10 | L4: 11 | M4: 12 | N4: 13 | O4: 14 | P4: 15 | Q4: 16 | R4: 17 | S4: 18 | T4: 19 | U4: 20 | V4: 21 | W4: 22 | X4: 23 | Y4: 24 | Z4: 25 | AA4: 26 | AB4: 27 | AC4: 28 | AD4: 29 | AE4: 30 | AF4: 31 | AG4: 32 | AH4: 33 | AI4: 34 | AJ4: 35 | AK4: 36 | AL4: 37 | AM4: 38 | AN4: 39 | AO4: 40 | AP4: 41 | AQ4: 42 | AR4: 43 | AS4: 44 | AT4: 45 | AU4: 46 | AV4: 47 | AW4: 48 | AX4: 49 | AY4: 50 | AZ4: 51 | BA4: 52 | BB4: 53 | BC4: 54 | BD4: 55 | BE4: 56 | BF4: 57 | BG4: 58 | BH4: 59 | BI4: 60
A5: Venda Assinatura | B5: =Receita!B13 -> 0 | C5: =Receita!C13 -> 0 | D5: =Receita!D13 -> 0 | E5: =Receita!E13 -> 0 | F5: =Receita!F13 -> 0 | G5: =Receita!G13 -> 0 | H5: =Receita!H13 -> 0 | I5: =Receita!I13 -> 0 | ... BI5: =Receita!BI13 -> 2312.5
A6: Venda Jogo 1 | B6: =Receita!B5 -> 4875 | C6: =Receita!C5 -> 4875 | D6: =Receita!D5 -> 4875 | E6: =Receita!E5 -> 4875 | F6: =Receita!F5 -> 4875 | G6: =Receita!G5 -> 4875 | H6: =Receita!H5 -> 4875 | I6: =Receita!I5 -> 4875 | ... BI6: =Receita!BI5 -> 6500
A7: Venda Jogo 2 | B7: =Receita!B9 -> 0 | C7: =Receita!C9 -> 0 | D7: =Receita!D9 -> 0 | E7: =Receita!E9 -> 0 | F7: =Receita!F9 -> 0 | G7: =Receita!G9 -> 0 | H7: =Receita!H9 -> 0 | I7: =Receita!I9 -> 0 | ... BI7: =Receita!BI9 -> 11458.333
A8: Receita total bruta | B8: =SUM(B5:B7) -> 4875 | C8: =SUM(C5:C7) -> 4875 | D8: =SUM(D5:D7) -> 4875 | E8: =SUM(E5:E7) -> 4875 | F8: =SUM(F5:F7) -> 4875 | G8: =SUM(G5:G7) -> 4875 | H8: =SUM(H5:H7) -> 4875 | I8: =SUM(I5:I7) -> 4875 | ... BI8: =SUM(BI5:BI7) -> 20270.833
A9: Impostos sobre a receita bruta | B9: =imp_fat*Resultados!B8 -> 762.9375 | C9: =imp_fat*Resultados!C8 -> 762.9375 | D9: =imp_fat*Resultados!D8 -> 762.9375 | E9: =imp_fat*Resultados!E8 -> 762.9375 | F9: =imp_fat*Resultados!F8 -> 762.9375 | G9: =imp_fat*Resultados!G8 -> 762.9375 | H9: =imp_fat*Resultados!H8 -> 762.9375 | I9: =imp_fat*Resultados!I8 -> 762.9375 | ... BI9: =imp_fat*Resultados!BI8 -> 3172.3854
A10: Receita líquida | B10: =B8-B9 -> 4112.0625 | C10: =C8-C9 -> 4112.0625 | D10: =D8-D9 -> 4112.0625 | E10: =E8-E9 -> 4112.0625 | F10: =F8-F9 -> 4112.0625 | G10: =G8-G9 -> 4112.0625 | H10: =H8-H9 -> 4112.0625 | I10: =I8-I9 -> 4112.0625 | ... BI10: =BI8-BI9 -> 17098.448
A11: Custos | B11: =Custos!B8 -> 945 | C11: =Custos!C8 -> 290 | D11: =Custos!D8 -> 290 | E11: =Custos!E8 -> 290 | F11: =Custos!F8 -> 290 | G11: =Custos!G8 -> 290 | H11: =Custos!H8 -> 290 | I11: =Custos!I8 -> 290 | ... BI11: =Custos!BI8 -> 475.24954
A12: Investimentos na infraestrutura | B12: =Investimentos_infra!B6 -> 6000 | C12: =Investimentos_infra!C6 -> 0 | D12: =Investimentos_infra!D6 -> 0 | E12: =Investimentos_infra!E6 -> 0 | F12: =Investimentos_infra!F6 -> 0 | G12: =Investimentos_infra!G6 -> 0 | H12: =Investimentos_infra!H6 -> 0 | I12: =Investimentos_infra!I6 -> 0 | ... BI12: =Investimentos_infra!BI6 -> 0
A13: Despesas | B13: =Despesas!B10 -> 3605 | C13: =Despesas!C10 -> 700 | D13: =Despesas!D10 -> 700 | E13: =Despesas!E10 -> 700 | F13: =Despesas!F10 -> 700 | G13: =Despesas!G10 -> 700 | H13: =Despesas!H10 -> 700 | I13: =Despesas!I10 -> 700 | ... BI13: =Despesas!BI10 -> 1252.1908
A14: Funcionários | B14: =Funcionários!B31 -> 6000 | C14: =Funcionários!C31 -> 6000 | D14: =Funcionários!D31 -> 6000 | E14: =Funcionários!E31 -> 6000 | F14: =Funcionários!F31 -> 6000 | G14: =Funcionários!G31 -> 6000 | H14: =Funcionários!H31 -> 6000 | I14: =Funcionários!I31 -> 6000 | ... BI14: =Funcionários!BI31 -> 12624.77
A15: Lucro Bruto | B15: =B10-SUM(B11:B14) -> -12437.938 | C15: =C10-SUM(C11:C14) -> -2877.9375 | D15: =D10-SUM(D11:D14) -> -2877.9375 | E15: =E10-SUM(E11:E14) -> -2877.9375 | F15: =F10-SUM(F11:F14) -> -2877.9375 | G15: =G10-SUM(G11:G14) -> -2877.9375 | H15: =H10-SUM(H11:H14) -> -2877.9375 | I15: =I10-SUM(I11:I14) -> -2877.9375 | ... BI15: =BI10-SUM(BI11:BI14) -> 2746.238
A16: IR | B16: =-IF(B15<0,0,0.25*B15) -> 0 | C16: =-IF(C15<0,0,0.25*C15) -> 0 | D16: =-IF(D15<0,0,0.25*D15) -> 0 | E16: =-IF(E15<0,0,0.25*E15) -> 0 | F16: =-IF(F15<0,0,0.25*F15) -> 0 | G16: =-IF(G15<0,0,0.25*G15) -> 0 | H16: =-IF(H15<0,0,0.25*H15) -> 0 | I16: =-IF(I15<0,0,0.25*I15) -> 0 | ... BI16: =-IF(BI15<0,0,0.25*BI15) -> -686.5595
A17: CSLL | B17: =-IF(B15<0,0,B15*0.09) -> 0 | C17: =-IF(C15<0,0,C15*0.09) -> 0 | D17: =-IF(D15<0,0,D15*0.09) -> 0 | E17: =-IF(E15<0,0,E15*0.09) -> 0 | F17: =-IF(F15<0,0,F15*0.09) -> 0 | G17: =-IF(G15<0,0,G15*0.09) -> 0 | H17: =-IF(H15<0,0,H15*0.09) -> 0 | I17: =-IF(I15<0,0,I15*0.09) -> 0 | ... BI17: =-IF(BI15<0,0,BI15*0.09) -> -247.16142
A18: Lucro Líquido | B18: =B15+B16+B17 -> -12437.938 | C18: =C15+C16+C17 -> -2877.9375 | D18: =D15+D16+D17 -> -2877.9375 | E18: =E15+E16+E17 -> -2877.9375 | F18: =F15+F16+F17 -> -2877.9375 | G18: =G15+G16+G17 -> -2877.9375 | H18: =H15+H16+H17 -> -2877.9375 | I18: =I15+I16+I17 -> -2877.9375 | ... BI18: =BI15+BI16+BI17 -> 1812.5171
A20: Caixa Acumulado [R$] | B20: =B18 -> -12437.938 | C20: =B20+C18 -> -15315.875 | D20: =C20+D18 -> -18193.812 | E20: =D20+E18 -> -21071.75 | F20: =E20+F18 -> -23949.688 | G20: =F20+G18 -> -26827.625 | H20: =G20+H18 -> -29705.562 | I20: =H20+I18 -> -32583.5 | J20: =I20+J18 -> -35461.438 | ... BI20: =BH20+BI18 -> 39272.276
A22: Resultados Anuais | B22: Ano 1 | C22: Ano 2 | D22: Ano 3 | E22: Ano 4 | F22: Ano 5
A23: =A5 -> Venda Assinatura | B23: =SUM(B5:M5) -> 0 | C23: =SUM(N5:Y5) -> 11250 | D23: =SUM(Z5:AK5) -> 7500 | E23: =SUM(AL5:AW5) -> 41250 | F23: =SUM(AX5:BI5) -> 27750
A24: =A6 -> Venda Jogo 1 | B24: =SUM(B6:M6) -> 58500 | C24: =SUM(N6:Y6) -> 94791.667 | D24: =SUM(Z6:AK6) -> 67708.333 | E24: =SUM(AL6:AW6) -> 97500 | F24: =SUM(AX6:BI6) -> 78000
A25: =A7 -> Venda Jogo 2 | B25: =SUM(B7:M7) -> 0 | C25: =SUM(N7:Y7) -> 0 | D25: =SUM(Z7:AK7) -> 0 | E25: =SUM(AL7:AW7) -> 220000 | F25: =SUM(AX7:BI7) -> 137500
A26: Receita total bruta | B26: =SUM(B8:M8) -> 58500 | C26: =SUM(N8:Y8) -> 106041.67 | D26: =SUM(Z8:AK8) -> 75208.333 | E26: =SUM(AL8:AW8) -> 358750 | F26: =SUM(F23:F25) -> 243250
A27: Impostos sobre a receita bruta | B27: =SUM(B9:M9) -> 9155.25 | C27: =SUM(N9:Y9) -> 16595.521 | D27: =SUM(Z9:AK9) -> 11770.104 | E27: =SUM(AL9:AW9) -> 56144.375 | F27: =SUM(AX9:BI9) -> 38068.625
A28: Receita líquida | B28: =SUM(B10:M10) -> 49344.75 | C28: =SUM(N10:Y10) -> 89446.146 | D28: =SUM(Z10:AK10) -> 63438.229 | E28: =SUM(AL10:AW10) -> 302605.62 | F28: =SUM(AX10:BI10) -> 205181.37
A29: Custos | B29: =SUM(B11:M11) -> 4135 | C29: =SUM(N11:Y11) -> 3494.4 | D29: =SUM(Z11:AK11) -> 3509.664 | E29: =SUM(AL11:AW11) -> 5432.7662 | F29: =SUM(AX11:BI11) -> 5702.9945
A30: Investimentos na infraestrutura | B30: =SUM(B12:M12) -> 6000 | C30: =SUM(N12:Y12) -> 1200 | D30: =SUM(Z12:AK12) -> 1200 | E30: =SUM(AL12:AW12) -> 3200 | F30: =SUM(AX12:BI12) -> 3600
A31: Despesas | B31: =SUM(B13:M13) -> 11305 | C31: =SUM(N13:Y13) -> 10938 | D31: =SUM(Z13:AK13) -> 11243.28 | E31: =SUM(AL13:AW13) -> 14956.877 | F31: =SUM(AX13:BI13) -> 18776.289
A32: Funcionários | B32: =SUM(B14:M14) -> 72000 | C32: =SUM(N14:Y14) -> 76320 | D32: =SUM(Z14:AK14) -> 83146.4 | E32: =SUM(AL14:AW14) -> 116719.57 | F32: =SUM(AX14:BI14) -> 151497.24
A33: Lucro Bruto | B33: =SUM(B15:M15) -> -44095.25 | C33: =SUM(N15:Y15) -> -2506.2542 | D33: =SUM(Z15:AK15) -> -35661.115 | E33: =SUM(AL15:AW15) -> 162296.41 | F33: =SUM(AX15:BI15) -> 25604.856
A34: IR | B34: =SUM(B16:M16) -> 0 | C34: =SUM(N16:Y16) -> -672.54688 | D34: =SUM(Z16:AK16) -> 0 | E34: =SUM(AL16:AW16) -> -40574.103 | F34: =SUM(AX16:BI16) -> -7552.1545
A35: CSLL | B35: =SUM(B17:M17) -> 0 | C35: =SUM(N17:Y17) -> -242.11688 | D35: =SUM(Z17:AK17) -> 0 | E35: =SUM(AL17:AW17) -> -14606.677 | F35: =SUM(AX17:BI17) -> -2718.7756
A36: Lucro Anual | B36: =SUM(B18:M18) -> -44095.25 | C36: =SUM(N18:Y18) -> -3420.9179 | D36: =SUM(Z18:AK18) -> -35661.115 | E36: =SUM(AL18:AW18) -> 107115.63 | F36: =SUM(AX18:BI18) -> 15333.926
A38: Taxa de desconto | B38: 0.15
A39: VPL | B39: {=NPV(B38,B36:F36)} -> 4489.2192
A40: APORTE | B40: 80000 | C40: equivale à máxima exposição do caixa (mês 36)
A41: TIR | B41: =IRR(B36:F36) -> 0.18341266 | C41: após 5 anos
A42: Pre-money valuation | B42: =B39 -> 4489.2192
A43: Post-money valuation | B43: =B42+B40 -> 84489.219
A44: Contrapartida ao investidor | B44: =B40/B43 -> 0.94686637
